prototype_python_library/__init__.py
prototype_python_library/calculations_with_logistic.py
prototype_python_library/logger.py
prototype_python_library/print_text.py
prototype_python_library/calculations/__init__.py
prototype_python_library/calculations/logger.py
prototype_python_library/calculations/logistic_model.py
prototype_python_library/connectors/__init__.py
prototype_python_library/forecasts/__init__.py
prototype_python_library/optimizers/__init__.py
prototype_python_library/utils/__init__.py
prototype_python_library/utils/logger.py
prototype_python_library/utils/test_utils.py
check_the_possibilities-0.0.20.dist-info/METADATA
check_the_possibilities-0.0.20.dist-info/WHEEL
check_the_possibilities-0.0.20.dist-info/top_level.txt
check_the_possibilities-0.0.20.dist-info/RECORD
