Metadata-Version: 2.1
Name: check-the-possibilities
Version: 0.0.20
Summary: PPL - Python Prototype Library
Home-page: https://github.com/AlexanderPetrenko83/prototype_python_library.git
Author: alexander_petrenko
Author-email: gd@reseco.ru
Requires-Python: >=3.12
Requires-Dist: pandas >=2.2.0
